{
    "Name": "CQ_BLITZ_03_b_2d",
    "Bundle": "d06d0c82",
    "Path": "assets/resources/events/cq_blitz_03_b_2d.asset",
    "Actions": [
        {
            "m_Name": "(Clone)(Clone)(Clone)(Clone)(Clone)",
            "Skip": 0,
            "Background": "black",
            "mBackGround": {
                "m_FileID": 0,
                "m_PathID": 0
            }
        },
        {
            "m_Name": "(Clone)(Clone)(Clone)(Clone)(Clone)",
            "Skip": 0
        },
        {
            "m_Name": "(Clone)(Clone)(Clone)(Clone)(Clone)",
            "Skip": 0,
            "FadeOut": 1,
            "ChangeColor": 0,
            "Async": 0,
            "FadeTime": 0.0
        },
        {
            "m_Name": "(Clone)(Clone)(Clone)(Clone)(Clone)",
            "Skip": 0,
            "Background": "bg83",
            "mBackGround": {
                "m_FileID": 0,
                "m_PathID": 0
            }
        },
        {
            "m_Name": "(Clone)(Clone)",
            "Skip": 0,
            "CharaID": "bli",
            "Flip": 0,
            "Position": 5,
            "StandTemplate": {
                "m_FileID": 0,
                "m_PathID": 5528542875535618604
            },
            "Emotion": "serious",
            "Async": 0,
            "Fade": 0,
            "FadeTime": 0.0
        },
        {
            "m_Name": "(Clone)(Clone)(Clone)",
            "Skip": 0,
            "CharaID": "gui",
            "Flip": 0,
            "Position": 1,
            "StandTemplate": {
                "m_FileID": 0,
                "m_PathID": 4143830858982075040
            },
            "Emotion": "serious",
            "Async": 0,
            "Fade": 0,
            "FadeTime": 0.0
        },
        {
            "m_Name": "(Clone)(Clone)(Clone)(Clone)(Clone)",
            "Skip": 0,
            "BGM": "0000"
        },
        {
            "m_Name": "(Clone)(Clone)(Clone)(Clone)(Clone)",
            "Skip": 0
        },
        {
            "m_Name": "(Clone)(Clone)(Clone)(Clone)(Clone)",
            "Skip": 0,
            "FadeOut": 0,
            "ChangeColor": 0,
            "Async": 0,
            "FadeTime": 1.0
        },
        {
            "m_Name": "(Clone)",
            "Skip": 0,
            "ActorID": "2DPlus",
            "CharaID": "gui",
            "UnitID": "UN_V2_GUILDFORD",
            "TextID": "CQ_BLITZ_03_b_2d.001",
            "Emotion": "",
            "Async": 0
        },
        {
            "m_Name": "(Clone)",
            "Skip": 0,
            "ActorID": "2DPlus",
            "CharaID": "bli",
            "UnitID": "UN_V2_BLITZ",
            "TextID": "CQ_BLITZ_03_b_2d.002",
            "Emotion": "",
            "Async": 0
        },
        {
            "m_Name": "",
            "Skip": 0,
            "ActorID": ""
        },
        {
            "m_Name": "",
            "Skip": 0,
            "SE": "SE_7641",
            "Loop": 0,
            "Interval": 1.0,
            "Count": 1,
            "async": 0,
            "SE_ID": ""
        },
        {
            "m_Name": "",
            "Skip": 0,
            "WaitSeconds": 1.0
        },
        {
            "m_Name": "",
            "Skip": 0,
            "BGM": "0028"
        },
        {
            "m_Name": "(Clone)",
            "Skip": 0,
            "ActorID": "2DPlus",
            "CharaID": "gui",
            "UnitID": "UN_V2_GUILDFORD",
            "TextID": "CQ_BLITZ_03_b_2d.003",
            "Emotion": "normal",
            "Async": 0
        },
        {
            "m_Name": "(Clone)",
            "Skip": 0,
            "ActorID": "2DPlus",
            "CharaID": "bli",
            "UnitID": "UN_V2_BLITZ",
            "TextID": "CQ_BLITZ_03_b_2d.004",
            "Emotion": "surprised",
            "Async": 0
        },
        {
            "m_Name": "(Clone)",
            "Skip": 0,
            "ActorID": "2DPlus",
            "CharaID": "gui",
            "UnitID": "UN_V2_GUILDFORD",
            "TextID": "CQ_BLITZ_03_b_2d.005",
            "Emotion": "",
            "Async": 0
        },
        {
            "m_Name": "(Clone)",
            "Skip": 0,
            "ActorID": "2DPlus",
            "CharaID": "bli",
            "UnitID": "UN_V2_BLITZ",
            "TextID": "CQ_BLITZ_03_b_2d.006",
            "Emotion": "sad",
            "Async": 0
        },
        {
            "m_Name": "",
            "Skip": 0,
            "ActorID": ""
        },
        {
            "m_Name": "",
            "Skip": 0,
            "FadeOut": 1,
            "ChangeColor": 0,
            "Async": 0,
            "FadeTime": 0.5
        },
        {
            "m_Name": "",
            "Skip": 0,
            "CharaID": "gui",
            "MoveTime": 0.0,
            "async": 0,
            "MoveTo": 3,
            "Emotion": "serious_f"
        },
        {
            "m_Name": "",
            "Skip": 0,
            "CharaID": "bli",
            "MoveTime": 0.0,
            "async": 0,
            "MoveTo": 0
        },
        {
            "m_Name": "(Clone)",
            "Skip": 0,
            "FadeOut": 0,
            "ChangeColor": 0,
            "Async": 0,
            "FadeTime": 0.5
        },
        {
            "m_Name": "(Clone)",
            "Skip": 0,
            "ActorID": "2DPlus",
            "CharaID": "gui",
            "UnitID": "UN_V2_GUILDFORD",
            "TextID": "CQ_BLITZ_03_b_2d.007",
            "Emotion": "",
            "Async": 0
        },
        {
            "m_Name": "(Clone)",
            "Skip": 0,
            "ActorID": "2DPlus",
            "CharaID": "gui",
            "UnitID": "UN_V2_GUILDFORD",
            "TextID": "CQ_BLITZ_03_b_2d.008",
            "Emotion": "",
            "Async": 0
        },
        {
            "m_Name": "(Clone)",
            "Skip": 0,
            "ActorID": "2DPlus",
            "CharaID": "gui",
            "UnitID": "UN_V2_GUILDFORD",
            "TextID": "CQ_BLITZ_03_b_2d.009",
            "Emotion": "",
            "Async": 0
        },
        {
            "m_Name": "(Clone)",
            "Skip": 0,
            "ActorID": "2DPlus",
            "CharaID": "gui",
            "UnitID": "UN_V2_GUILDFORD",
            "TextID": "CQ_BLITZ_03_b_2d.010",
            "Emotion": "",
            "Async": 0
        },
        {
            "m_Name": "",
            "Skip": 0,
            "ActorID": ""
        },
        {
            "m_Name": "(Clone)",
            "Skip": 0,
            "FadeOut": 1,
            "ChangeColor": 0,
            "Async": 0,
            "FadeTime": 0.5
        },
        {
            "m_Name": "(Clone)",
            "Skip": 0,
            "CharaID": "bli",
            "MoveTime": 0.0,
            "async": 0,
            "MoveTo": 3,
            "Emotion": "sad_f"
        },
        {
            "m_Name": "(Clone)(Clone)",
            "Skip": 0,
            "CharaID": "gui",
            "MoveTime": 0.0,
            "async": 0,
            "MoveTo": 0,
            "Emotion": "normal"
        },
        {
            "m_Name": "(Clone)(Clone)",
            "Skip": 0,
            "FadeOut": 0,
            "ChangeColor": 0,
            "Async": 0,
            "FadeTime": 0.5
        },
        {
            "m_Name": "(Clone)",
            "Skip": 0,
            "ActorID": "2DPlus",
            "CharaID": "bli",
            "UnitID": "UN_V2_BLITZ",
            "TextID": "CQ_BLITZ_03_b_2d.011",
            "Emotion": "serious_f",
            "Async": 0
        },
        {
            "m_Name": "(Clone)",
            "Skip": 0,
            "ActorID": "2DPlus",
            "CharaID": "bli",
            "UnitID": "UN_V2_BLITZ",
            "TextID": "CQ_BLITZ_03_b_2d.012",
            "Emotion": "",
            "Async": 0
        },
        {
            "m_Name": "",
            "Skip": 0,
            "ActorID": ""
        },
        {
            "m_Name": "(Clone)(Clone)",
            "Skip": 0,
            "FadeOut": 1,
            "ChangeColor": 0,
            "Async": 0,
            "FadeTime": 0.5
        },
        {
            "m_Name": "(Clone)(Clone)",
            "Skip": 0,
            "CharaID": "bli",
            "MoveTime": 0.0,
            "async": 0,
            "MoveTo": 5,
            "Emotion": "serious"
        },
        {
            "m_Name": "",
            "Skip": 0,
            "CharaID": "gui",
            "MoveTime": 0.0,
            "async": 0,
            "MoveTo": 1,
            "Emotion": "serious"
        },
        {
            "m_Name": "(Clone)(Clone)(Clone)",
            "Skip": 0,
            "FadeOut": 0,
            "ChangeColor": 0,
            "Async": 0,
            "FadeTime": 0.5
        },
        {
            "m_Name": "(Clone)",
            "Skip": 0,
            "ActorID": "2DPlus",
            "CharaID": "gui",
            "UnitID": "UN_V2_GUILDFORD",
            "TextID": "CQ_BLITZ_03_b_2d.013",
            "Emotion": "normal",
            "Async": 0
        },
        {
            "m_Name": "(Clone)",
            "Skip": 0,
            "ActorID": "2DPlus",
            "CharaID": "gui",
            "UnitID": "UN_V2_GUILDFORD",
            "TextID": "CQ_BLITZ_03_b_2d.014",
            "Emotion": "",
            "Async": 0
        },
        {
            "m_Name": "(Clone)",
            "Skip": 0,
            "ActorID": "2DPlus",
            "CharaID": "gui",
            "UnitID": "UN_V2_GUILDFORD",
            "TextID": "CQ_BLITZ_03_b_2d.015",
            "Emotion": "",
            "Async": 0
        },
        {
            "m_Name": "(Clone)",
            "Skip": 0,
            "ActorID": "2DPlus",
            "CharaID": "bli",
            "UnitID": "UN_V2_BLITZ",
            "TextID": "CQ_BLITZ_03_b_2d.016",
            "Emotion": "surprised",
            "Async": 0
        },
        {
            "m_Name": "(Clone)",
            "Skip": 0,
            "ActorID": "2DPlus",
            "CharaID": "gui",
            "UnitID": "UN_V2_GUILDFORD",
            "TextID": "CQ_BLITZ_03_b_2d.017",
            "Emotion": "serious",
            "Async": 0
        },
        {
            "m_Name": "(Clone)",
            "Skip": 0,
            "ActorID": "2DPlus",
            "CharaID": "bli",
            "UnitID": "UN_V2_BLITZ",
            "TextID": "CQ_BLITZ_03_b_2d.018",
            "Emotion": "",
            "Async": 0
        },
        {
            "m_Name": "(Clone)",
            "Skip": 0,
            "ActorID": "2DPlus",
            "CharaID": "gui",
            "UnitID": "UN_V2_GUILDFORD",
            "TextID": "CQ_BLITZ_03_b_2d.019",
            "Emotion": "normal",
            "Async": 0
        },
        {
            "m_Name": "(Clone)",
            "Skip": 0,
            "ActorID": "2DPlus",
            "CharaID": "gui",
            "UnitID": "UN_V2_GUILDFORD",
            "TextID": "CQ_BLITZ_03_b_2d.020",
            "Emotion": "",
            "Async": 0
        },
        {
            "m_Name": "(Clone)",
            "Skip": 0,
            "ActorID": "2DPlus",
            "CharaID": "gui",
            "UnitID": "UN_V2_GUILDFORD",
            "TextID": "CQ_BLITZ_03_b_2d.021",
            "Emotion": "serious",
            "Async": 0
        },
        {
            "m_Name": "(Clone)",
            "Skip": 0,
            "ActorID": "2DPlus",
            "CharaID": "bli",
            "UnitID": "UN_V2_BLITZ",
            "TextID": "CQ_BLITZ_03_b_2d.022",
            "Emotion": "sad",
            "Async": 0
        },
        {
            "m_Name": "(Clone)",
            "Skip": 0,
            "ActorID": "2DPlus",
            "CharaID": "gui",
            "UnitID": "UN_V2_GUILDFORD",
            "TextID": "CQ_BLITZ_03_b_2d.023",
            "Emotion": "normal",
            "Async": 0
        },
        {
            "m_Name": "(Clone)",
            "Skip": 0,
            "ActorID": "2DPlus",
            "CharaID": "gui",
            "UnitID": "UN_V2_GUILDFORD",
            "TextID": "CQ_BLITZ_03_b_2d.024",
            "Emotion": "",
            "Async": 0
        },
        {
            "m_Name": "(Clone)",
            "Skip": 0,
            "ActorID": "2DPlus",
            "CharaID": "bli",
            "UnitID": "UN_V2_BLITZ",
            "TextID": "CQ_BLITZ_03_b_2d.025",
            "Emotion": "surprised",
            "Async": 0
        },
        {
            "m_Name": "(Clone)",
            "Skip": 0,
            "ActorID": "2DPlus",
            "CharaID": "gui",
            "UnitID": "UN_V2_GUILDFORD",
            "TextID": "CQ_BLITZ_03_b_2d.026",
            "Emotion": "",
            "Async": 0
        },
        {
            "m_Name": "(Clone)",
            "Skip": 0,
            "ActorID": "2DPlus",
            "CharaID": "bli",
            "UnitID": "UN_V2_BLITZ",
            "TextID": "CQ_BLITZ_03_b_2d.027",
            "Emotion": "smile",
            "Async": 0
        },
        {
            "m_Name": "(Clone)",
            "Skip": 0,
            "ActorID": "2DPlus",
            "CharaID": "bli",
            "UnitID": "UN_V2_BLITZ",
            "TextID": "CQ_BLITZ_03_b_2d.028",
            "Emotion": "normal",
            "Async": 0
        },
        {
            "m_Name": "(Clone)",
            "Skip": 0,
            "ActorID": "2DPlus",
            "CharaID": "bli",
            "UnitID": "UN_V2_BLITZ",
            "TextID": "CQ_BLITZ_03_b_2d.029",
            "Emotion": "smile",
            "Async": 0
        },
        {
            "m_Name": "(Clone)",
            "Skip": 0,
            "ActorID": "2DPlus",
            "CharaID": "gui",
            "UnitID": "UN_V2_GUILDFORD",
            "TextID": "CQ_BLITZ_03_b_2d.030",
            "Emotion": "smile",
            "Async": 0
        },
        {
            "m_Name": "",
            "Skip": 0,
            "ActorID": ""
        },
        {
            "m_Name": "",
            "Skip": 0,
            "SE": "SE_9252",
            "Loop": 0,
            "Interval": 1.0,
            "Count": 1,
            "async": 0,
            "SE_ID": ""
        },
        {
            "m_Name": "",
            "Skip": 0,
            "WaitSeconds": 1.0
        },
        {
            "m_Name": "(Clone)",
            "Skip": 0,
            "ActorID": "2DPlus",
            "CharaID": "inq",
            "UnitID": "UN_EV_INQUISITION",
            "TextID": "CQ_BLITZ_03_b_2d.031",
            "Emotion": "",
            "Async": 0
        },
        {
            "m_Name": "(Clone)",
            "Skip": 0,
            "ActorID": "2DPlus",
            "CharaID": "gui",
            "UnitID": "UN_V2_GUILDFORD",
            "TextID": "CQ_BLITZ_03_b_2d.032",
            "Emotion": "normal",
            "Async": 0
        },
        {
            "m_Name": "(Clone)",
            "Skip": 0,
            "ActorID": "2DPlus",
            "CharaID": "bli",
            "UnitID": "UN_V2_BLITZ",
            "TextID": "CQ_BLITZ_03_b_2d.033",
            "Emotion": "surprised",
            "Async": 0
        },
        {
            "m_Name": "(Clone)",
            "Skip": 0,
            "ActorID": "2DPlus",
            "CharaID": "gui",
            "UnitID": "UN_V2_GUILDFORD",
            "TextID": "CQ_BLITZ_03_b_2d.034",
            "Emotion": "",
            "Async": 0
        },
        {
            "m_Name": "(Clone)",
            "Skip": 0,
            "ActorID": "2DPlus",
            "CharaID": "bli",
            "UnitID": "UN_V2_BLITZ",
            "TextID": "CQ_BLITZ_03_b_2d.035",
            "Emotion": "",
            "Async": 0
        },
        {
            "m_Name": "(Clone)",
            "Skip": 0,
            "ActorID": "2DPlus",
            "CharaID": "gui",
            "UnitID": "UN_V2_GUILDFORD",
            "TextID": "CQ_BLITZ_03_b_2d.036",
            "Emotion": "",
            "Async": 0
        },
        {
            "m_Name": "(Clone)",
            "Skip": 0,
            "ActorID": "2DPlus",
            "CharaID": "bli",
            "UnitID": "UN_V2_BLITZ",
            "TextID": "CQ_BLITZ_03_b_2d.037",
            "Emotion": "smile",
            "Async": 0
        },
        {
            "m_Name": "",
            "Skip": 0,
            "ActorID": ""
        },
        {
            "m_Name": "(Clone)",
            "Skip": 0,
            "SE": "SE_2005",
            "Loop": 1,
            "Interval": 0.4000000059604645,
            "Count": 2,
            "async": 1,
            "SE_ID": ""
        },
        {
            "m_Name": "",
            "Skip": 0,
            "CharaID": "bli",
            "MoveTime": 0.4000000059604645,
            "async": 0,
            "MoveTo": 3
        },
        {
            "m_Name": "",
            "Skip": 0,
            "SE": "SE_9134",
            "Loop": 0,
            "Interval": 1.0,
            "Count": 1,
            "async": 0,
            "SE_ID": ""
        },
        {
            "m_Name": "",
            "Skip": 0,
            "WaitSeconds": 0.4000000059604645
        },
        {
            "m_Name": "",
            "Skip": 0,
            "SE": "SE_2005",
            "Loop": 1,
            "Interval": 0.4000000059604645,
            "Count": 2,
            "async": 1,
            "SE_ID": ""
        },
        {
            "m_Name": "(Clone)",
            "Skip": 0,
            "CharaID": "bli",
            "MoveTime": 0.4000000059604645,
            "async": 0,
            "MoveTo": 5
        },
        {
            "m_Name": "(Clone)",
            "Skip": 0,
            "ActorID": "2DPlus",
            "CharaID": "gui",
            "UnitID": "UN_V2_GUILDFORD",
            "TextID": "CQ_BLITZ_03_b_2d.038",
            "Emotion": "smile",
            "Async": 0
        },
        {
            "m_Name": "(Clone)",
            "Skip": 0,
            "ActorID": "2DPlus",
            "CharaID": "bli",
            "UnitID": "UN_V2_BLITZ",
            "TextID": "CQ_BLITZ_03_b_2d.039",
            "Emotion": "",
            "Async": 0
        },
        {
            "m_Name": "(Clone)",
            "Skip": 0,
            "ActorID": "2DPlus",
            "CharaID": "bli",
            "UnitID": "UN_V2_BLITZ",
            "TextID": "CQ_BLITZ_03_b_2d.040",
            "Emotion": "",
            "Async": 0
        },
        {
            "m_Name": "(Clone)",
            "Skip": 0,
            "ActorID": ""
        },
        {
            "m_Name": "(Clone)(Clone)(Clone)(Clone)(Clone)(Clone)(Clone)",
            "Skip": 0
        },
        {
            "m_Name": "(Clone)(Clone)(Clone)(Clone)(Clone)(Clone)(Clone)(Clone)(Clone)(Clone)",
            "Skip": 0,
            "ActorID": ""
        },
        {
            "m_Name": "(Clone)(Clone)(Clone)(Clone)(Clone)(Clone)(Clone)(Clone)(Clone)(Clone)",
            "Skip": 0,
            "FadeOut": 1,
            "ChangeColor": 0,
            "Async": 0,
            "FadeTime": 2.0
        },
        {
            "m_Name": "(Clone)(Clone)(Clone)(Clone)",
            "Skip": 0,
            "BGM": "0000"
        },
        {
            "m_Name": "(Clone)(Clone)(Clone)",
            "Skip": 0,
            "WaitSeconds": 1.5
        },
        {
            "m_Name": "(Clone)(Clone)(Clone)(Clone)",
            "Skip": 0,
            "CharaID": "bli",
            "MoveTime": 0.0,
            "async": 0,
            "MoveTo": 0
        },
        {
            "m_Name": "(Clone)(Clone)(Clone)(Clone)(Clone)",
            "Skip": 0,
            "CharaID": "gui",
            "MoveTime": 0.0,
            "async": 0,
            "MoveTo": 0
        },
        {
            "m_Name": "(Clone)(Clone)(Clone)(Clone)",
            "Skip": 0,
            "ResourceID": "Demo/EventAssets/2D/demo_cut_blitz",
            "ObjectID": "demo_cut",
            "Persistent": 0,
            "Position": {
                "x": 0.0,
                "y": 0.0
            },
            "Order": 0,
            "CharaID": "",
            "ChildOrder": 0
        },
        {
            "m_Name": "(Clone)(Clone)(Clone)(Clone)",
            "Skip": 0,
            "WaitSeconds": 7.5
        },
        {
            "m_Name": "(Clone)(Clone)(Clone)(Clone)(Clone)(Clone)(Clone)(Clone)(Clone)(Clone)",
            "Skip": 0,
            "BGM": "0000"
        },
        {
            "m_Name": "(Clone)(Clone)(Clone)(Clone)(Clone)(Clone)(Clone)(Clone)(Clone)(Clone)",
            "Skip": 0,
            "WaitSeconds": 1.5
        }
    ]
}